README.md
setup.py
pyracing/__init__.py
pyracing/client.py
pyracing/constants.py
pyracing/helpers.py
pyracing/exceptions/__init__.py
pyracing/exceptions/authentication_error.py
pyracing/response_objects/__init__.py
pyracing/response_objects/career_stats.py
pyracing/response_objects/chart_data.py
pyracing/response_objects/historical_data.py
pyracing/response_objects/iracing_data.py
pyracing/response_objects/league_data.py
pyracing/response_objects/session_data.py
pyracing/response_objects/upcoming_events.py
pyracing_bullethell.egg-info/PKG-INFO
pyracing_bullethell.egg-info/SOURCES.txt
pyracing_bullethell.egg-info/dependency_links.txt
pyracing_bullethell.egg-info/not-zip-safe
pyracing_bullethell.egg-info/requires.txt
pyracing_bullethell.egg-info/top_level.txt