Metadata-Version: 2.1
Name: pyracing-bullethell
Version: 0.1.2
Summary: A complete overhaul of ir_webstats; pyracing is an API wrapper for simracing service "iRacing" that queries known URL endpoints and returns JSON data that is accessible through objects instead of dictionaries.
Home-page: https://github.com/bULLETHELL/pyracing.git
Author: Jacob Anderson & Xander Riga
License: UNKNOWN
Project-URL: Documentation, https://esterni.github.io/pyracing/
Platform: UNKNOWN
Classifier: Programming Language :: Python :: 3
Classifier: License :: OSI Approved :: MIT License
Classifier: Operating System :: OS Independent
Requires-Python: >=3.8
